.gitignore
LICENSE
MANIFEST.in
README.rst
pyproject.toml
requirements.txt
setup.py
.github/workflows/documentation.yml
.github/workflows/package_release.yml
.github/workflows/pull_request.yml
.github/workflows/pypi.yml
.github/workflows/tests.yml
docs/.gitkeep
docs/Makefile
docs/api.rst
docs/conf.py
docs/guide.rst
docs/index.rst
docs/make.bat
docs/tutorial.rst
src/icikt/.gitkeep
src/icikt/__init__.py
src/icikt/__main__.py
src/icikt/_version.py
src/icikt/c_kendall_dis.c
src/icikt/c_kendall_dis.pyx
src/icikt/kendall_dis.py
src/icikt/left_censorship.py
src/icikt/methods.py
src/icikt/utility.py
src/icikt.egg-info/PKG-INFO
src/icikt.egg-info/SOURCES.txt
src/icikt.egg-info/dependency_links.txt
src/icikt.egg-info/entry_points.txt
src/icikt.egg-info/requires.txt
src/icikt.egg-info/top_level.txt
test/.gitkeep
test/small_sample.csv
test/small_sample.tsv
test/test_cli.py
test/test_icikt.py
test/test_left_censor.py