Metadata-Version: 2.1
Name: icikt
Version: 1.5.3
Summary: Python tool to calculate the KendallTau correlation coefficients.
License: A modified Clear BSD License
Project-URL: GitHub, https://github.com/MoseleyBioinformaticsLab/icikt
Keywords: icikendalltau,missing values
Requires-Python: >=3.8
License-File: LICENSE
Requires-Dist: numpy>=1.24.1
Requires-Dist: scipy>=1.4.1
Requires-Dist: docopt>=0.6.2
Requires-Dist: Cython>=3.0.0
Requires-Dist: sphinx_rtd_theme>=1.0.0
